blmpy/__init__.py
blmpy/blmdata.py
blmpy/blmjson.py
blmpy/blmlib.py
blmpy/blmos.py
blmpy-0.0.10.dist-info/METADATA
blmpy-0.0.10.dist-info/WHEEL
blmpy-0.0.10.dist-info/top_level.txt
blmpy-0.0.10.dist-info/RECORD
