Metadata-Version: 2.1
Name: blmpy
Version: 0.0.10
Summary: Bluemanoid Package
Home-page: UNKNOWN
Author: Gautier Rio
Author-email: gautier.rio@bluemanoid.com
License: UNKNOWN
Keywords: python,Bluemanoid,BLM
Platform: UNKNOWN
Classifier: Development Status :: 3 - Alpha
Classifier: Intended Audience :: Education
Classifier: Programming Language :: Python :: 2
Classifier: Programming Language :: Python :: 3
Classifier: Operating System :: MacOS :: MacOS X
Classifier: Operating System :: Microsoft :: Windows
